README.rst
setup.py
trop/__init__.py
troposphere_cli.egg-info/PKG-INFO
troposphere_cli.egg-info/SOURCES.txt
troposphere_cli.egg-info/dependency_links.txt
troposphere_cli.egg-info/entry_points.txt
troposphere_cli.egg-info/requires.txt
troposphere_cli.egg-info/top_level.txt