Metadata-Version: 1.0
Name: troposphere-cli
Version: 0.1
Summary: Troposphere Command Line Interface
Home-page: https://github.com/Omixy/troposphere-cli
Author: jean-philippe serafin
Author-email: tech@omixy.com
License: MIT
Platform: UNKNOWN
